stranding/__init__.py
stranding/exceptions.py
stranding/lib.py
stranding/stranding.py
tests/__init__.py
tests/test_functional.py
stranding-0.2.0.dist-info/LICENSE
stranding-0.2.0.dist-info/METADATA
stranding-0.2.0.dist-info/WHEEL
stranding-0.2.0.dist-info/entry_points.txt
stranding-0.2.0.dist-info/top_level.txt
stranding-0.2.0.dist-info/RECORD
