Metadata-Version: 2.1
Name: stranding
Version: 0.2.0
Summary: Determine genome stranding for sequences mapped to a human reference assembly
Home-page: https://github.com/23andMe/stranding
Author: 23andMe Engineering
Author-email: mstrand@23andme.com
License: MIT
Download-URL: https://github.com/23andMe/stranding/tarball/0.2.0
Platform: UNKNOWN
Classifier: Intended Audience :: Developers
Classifier: License :: OSI Approved :: MIT License
Classifier: Programming Language :: Python
Classifier: Programming Language :: Python :: 2
Classifier: Programming Language :: Python :: 2.7
License-File: LICENSE
Requires-Dist: seqseek
Requires-Dist: biopython
